bytedflow_idp/__init__.py
bytedflow_idp-0.0.1.dist-info/METADATA
bytedflow_idp-0.0.1.dist-info/WHEEL
bytedflow_idp-0.0.1.dist-info/top_level.txt
bytedflow_idp-0.0.1.dist-info/RECORD
